subreddit_mirror-1.1.0.dist-info/METADATA
subreddit_mirror-1.1.0.dist-info/RECORD
subreddit_mirror-1.1.0.dist-info/WHEEL
subreddit_mirror-1.1.0.dist-info/entry_points.txt
subreddit_mirror-1.1.0.dist-info/top_level.txt
subredditmirror/__init__.py
subredditmirror/__main__.py
subredditmirror/exceptions.py
subredditmirror/mirror.py
