Metadata-Version: 2.1
Name: subreddit-mirror
Version: 1.1.0
Summary: A script to copy posts from one subreddit to another.
Home-page: UNKNOWN
Author: Jacob Patterson
Author-email: jacob@jacobpa.com
License: GPLv3
Project-URL: Github, https://github.com/jacobpa/subreddit-mirror
Keywords: reddit mirror crosspost bot script
Platform: UNKNOWN
Classifier: Programming Language :: Python :: 3.6
Classifier: Operating System :: OS Independent
Classifier: Natural Language :: English
Requires-Dist: progress (==1.4)
Requires-Dist: praw (==5.4.0)
